README.rst
setup.py
myslicelib/__init__.py
myslicelib.egg-info/PKG-INFO
myslicelib.egg-info/SOURCES.txt
myslicelib.egg-info/dependency_links.txt
myslicelib.egg-info/top_level.txt