Metadata-Version: 1.1
Name: myslicelib
Version: 1.0.1
Summary: MySlice Library
Home-page: http://gitlab.noc.onelab.eu/onelab/myslicelib
Author: OneLab
Author-email: admin@onelab.eu
License: MIT
Keywords: myslice testbed api
Platform: UNKNOWN
Classifier: Development Status :: 5 - Production/Stable
Classifier: Intended Audience :: Developers
Classifier: Topic :: Software Development :: Build Tools
Classifier: License :: OSI Approved :: MIT License
Classifier: Programming Language :: Python :: 3
Classifier: Programming Language :: Python :: 3.5
Classifier: Programming Language :: Python :: 3.6
